incase/__init__.py
incase/core.py
incase/extra.py
incase/middleware.py
incase-0.0.12.dist-info/LICENSE
incase-0.0.12.dist-info/METADATA
incase-0.0.12.dist-info/WHEEL
incase-0.0.12.dist-info/entry_points.txt
incase-0.0.12.dist-info/top_level.txt
incase-0.0.12.dist-info/RECORD
