Metadata-Version: 2.1
Name: incase
Version: 0.0.12
Summary: A word case management library with too many features (just in case).
Author-email: Patrick Shechet <patrick.shechet@gmail.com>
License: MIT
Project-URL: Repository, https://github.com/kajuberdut/incase
Requires-Python: >=3.10
License-File: LICENSE
Provides-Extra: middleware
Requires-Dist: starlette ; extra == 'middleware'
